LICENSE
README.md
setup.py
fixprice_api/__init__.py
fixprice_api/abstraction.py
fixprice_api/api.py
fixprice_api/manager.py
fixprice_api.egg-info/PKG-INFO
fixprice_api.egg-info/SOURCES.txt
fixprice_api.egg-info/dependency_links.txt
fixprice_api.egg-info/requires.txt
fixprice_api.egg-info/top_level.txt