Metadata-Version: 2.1
Name: fixprice-api
Version: 0.1.1
Summary: A Python API client for FixPrice catalog
Home-page: https://github.com/Open-Inflation/fixprice_api
Author: Miskler
License: UNKNOWN
Platform: UNKNOWN
Classifier: Programming Language :: Python :: 3
Classifier: License :: OSI Approved :: MIT License
Classifier: Operating System :: OS Independent
Requires-Python: >=3.10
License-File: LICENSE
